skyant/tools/__init__.py
skyant/tools/auth/__init__.py
skyant/tools/auth/_gcp.py
skyant/tools/crypto/__init__.py
skyant/tools/crypto/_aes.py
skyant/tools/duty/__init__.py
skyant/tools/duty/general.py
skyant/tools/duty/pypi.py
skyant/tools/duty/venv.py
skyant_tools-0.0.2.post1.dist-info/LICENSE
skyant_tools-0.0.2.post1.dist-info/METADATA
skyant_tools-0.0.2.post1.dist-info/WHEEL
skyant_tools-0.0.2.post1.dist-info/top_level.txt
skyant_tools-0.0.2.post1.dist-info/RECORD
