Metadata-Version: 2.1
Name: skyant-tools
Version: 0.0.2.post1
Summary: Tools for a working with GCP.
Home-page: https://skyant.dev
Author: Iurii Tarasenko
Author-email: info@skyant.dev
License: MIT
Project-URL: Source & issues, https://gitlab.com/skyant/python/tools
Project-URL: Documentation, https://docs.skyant.dev/projects/tools
Keywords: pydantic,api,rest,GCP
Classifier: Programming Language :: Python :: 3.10
Classifier: Intended Audience :: Developers
Classifier: Intended Audience :: Information Technology
Classifier: Topic :: Software Development :: Libraries :: Python Modules
Requires-Python: >=3.10
License-File: LICENSE
Requires-Dist: google-auth
Requires-Dist: pyyaml
Requires-Dist: flask
Requires-Dist: python-jose
Requires-Dist: requests
Requires-Dist: duty
